monaco/__init__.py
monaco/index.html
monaco/index.js
monaco/monaco_widget.py
monaco/_pyinstaller/__init__.py
monaco/_pyinstaller/hook-monaco.py
monaco/monaco-editor/CHANGELOG.md
monaco/monaco-editor/LICENSE
monaco/monaco-editor/README.md
monaco/monaco-editor/ThirdPartyNotices.txt
monaco/monaco-editor/monaco.d.ts
monaco/monaco-editor/package.json
monaco/monaco-editor/min/vs/loader.js
monaco/monaco-editor/min/vs/base/browser/ui/codicons/codicon/codicon.ttf
monaco/monaco-editor/min/vs/base/worker/workerMain.js
monaco/monaco-editor/min/vs/basic-languages/abap/abap.js
monaco/monaco-editor/min/vs/basic-languages/apex/apex.js
monaco/monaco-editor/min/vs/basic-languages/azcli/azcli.js
monaco/monaco-editor/min/vs/basic-languages/bat/bat.js
monaco/monaco-editor/min/vs/basic-languages/bicep/bicep.js
monaco/monaco-editor/min/vs/basic-languages/cameligo/cameligo.js
monaco/monaco-editor/min/vs/basic-languages/clojure/clojure.js
monaco/monaco-editor/min/vs/basic-languages/coffee/coffee.js
monaco/monaco-editor/min/vs/basic-languages/cpp/cpp.js
monaco/monaco-editor/min/vs/basic-languages/csharp/csharp.js
monaco/monaco-editor/min/vs/basic-languages/csp/csp.js
monaco/monaco-editor/min/vs/basic-languages/css/css.js
monaco/monaco-editor/min/vs/basic-languages/dart/dart.js
monaco/monaco-editor/min/vs/basic-languages/dockerfile/dockerfile.js
monaco/monaco-editor/min/vs/basic-languages/ecl/ecl.js
monaco/monaco-editor/min/vs/basic-languages/elixir/elixir.js
monaco/monaco-editor/min/vs/basic-languages/flow9/flow9.js
monaco/monaco-editor/min/vs/basic-languages/freemarker2/freemarker2.js
monaco/monaco-editor/min/vs/basic-languages/fsharp/fsharp.js
monaco/monaco-editor/min/vs/basic-languages/go/go.js
monaco/monaco-editor/min/vs/basic-languages/graphql/graphql.js
monaco/monaco-editor/min/vs/basic-languages/handlebars/handlebars.js
monaco/monaco-editor/min/vs/basic-languages/hcl/hcl.js
monaco/monaco-editor/min/vs/basic-languages/html/html.js
monaco/monaco-editor/min/vs/basic-languages/ini/ini.js
monaco_qt-0.2.0.dist-info/LICENSE
monaco_qt-0.2.0.dist-info/METADATA
monaco_qt-0.2.0.dist-info/WHEEL
monaco_qt-0.2.0.dist-info/top_level.txt
monaco_qt-0.2.0.dist-info/RECORD
