Metadata-Version: 2.1
Name: monaco-qt
Version: 0.2.0
Summary: The Monaco editor as a Qt Widget
Author-email: David Kincaid <daelonsuzuka@gmail.com>
License: MIT License
Project-URL: Homepage, https://github.com/DaelonSuzuka/monaco-qt
Project-URL: Repository, https://github.com/DaelonSuzuka/monaco-qt
Project-URL: Issues, https://github.com/qtstrap/qtstrap/issues
Keywords: qtstrap,qt,pyqt,monaco,text editor
Classifier: Development Status :: 4 - Beta
Classifier: Intended Audience :: Developers
Classifier: Topic :: Software Development :: Widget Sets
Classifier: Operating System :: OS Independent
Classifier: License :: OSI Approved :: MIT License
Classifier: Programming Language :: Python :: 3
Classifier: Programming Language :: Python :: 3.9
Classifier: Programming Language :: Python :: 3.10
Classifier: Programming Language :: Python :: 3.11
Classifier: Programming Language :: Python :: 3.12
Classifier: Programming Language :: Python :: 3.13
Requires-Python: >=3.9
License-File: LICENSE
Requires-Dist: qtpy
